LICENSE
MANIFEST.in
README.md
VERSION
requirements.txt
setup.py
popug_legacy_sdk/__init__.py
popug_legacy_sdk.egg-info/PKG-INFO
popug_legacy_sdk.egg-info/SOURCES.txt
popug_legacy_sdk.egg-info/dependency_links.txt
popug_legacy_sdk.egg-info/not-zip-safe
popug_legacy_sdk.egg-info/requires.txt
popug_legacy_sdk.egg-info/top_level.txt
popug_legacy_sdk/auth/__init__.py
popug_legacy_sdk/auth/permissions.py
popug_legacy_sdk/auth/token.py
popug_legacy_sdk/config/__init__.py
popug_legacy_sdk/config/auth.py
popug_legacy_sdk/config/database.py
popug_legacy_sdk/config/global_settings.py
popug_legacy_sdk/config/redis.py
popug_legacy_sdk/database/__init__.py
popug_legacy_sdk/database/base.py
popug_legacy_sdk/database/user.py
popug_legacy_sdk/redis/__init__.py
popug_legacy_sdk/redis/redis.py
popug_legacy_sdk/schemas/__init__.py