Metadata-Version: 2.1
Name: popug-legacy-sdk
Version: 0.0.3
Summary: Package for popug_legacy project
Home-page: https://github.com/harroowd/popug_legacy
Author: Andrei Kazlou
Author-email: andrey.vs1998@gmail.com
License-File: LICENSE
